woodwork/__init__.py
woodwork/__main__.py
woodwork/argument_parser.py
woodwork/config_parser.py
woodwork/dependencies.py
woodwork/errors.py
woodwork/exports.py
woodwork/generate_exports.py
woodwork/globals.py
woodwork/helper_functions.py
woodwork/registry.py
woodwork/components/__init__.py
woodwork/components/component.py
woodwork/components/task_master.py
woodwork/components/apis/__init__.py
woodwork/components/apis/api.py
woodwork/components/apis/functions.py
woodwork/components/apis/web.py
woodwork/components/core/__init__.py
woodwork/components/core/command_line.py
woodwork/components/core/core.py
woodwork/components/decomposers/__init__.py
woodwork/components/decomposers/decomposer.py
woodwork/components/decomposers/llm.py
woodwork/components/inputs/__init__.py
woodwork/components/inputs/command_line.py
woodwork/components/inputs/inputs.py
woodwork/components/inputs/keyword_voice.py
woodwork/components/inputs/push_to_talk.py
woodwork/components/knowledge_bases/__init__.py
woodwork/components/knowledge_bases/knowledge_base.py
woodwork/components/knowledge_bases/graph_databases/__init__.py
woodwork/components/knowledge_bases/graph_databases/graph_database.py
woodwork/components/knowledge_bases/graph_databases/neo4j.py
woodwork/components/knowledge_bases/text_files/__init__.py
woodwork/components/knowledge_bases/text_files/text_file.py
woodwork/components/knowledge_bases/vector_databases/__init__.py
woodwork/components/knowledge_bases/vector_databases/chroma.py
woodwork/components/knowledge_bases/vector_databases/vector_database.py
woodwork/components/llms/__init__.py
woodwork/components/llms/hugging_face.py
woodwork/components/llms/llm.py
woodwork/components/llms/ollama.py
woodwork/components/llms/openai.py
woodwork/components/memory/__init__.py
woodwork/components/memory/memory.py
woodwork/components/memory/short_term.py
woodwork/components/outputs/outputs.py
woodwork/components/outputs/voice.py
woodwork/config/.env.example
woodwork/config/log_config.json
woodwork_engine-0.2.11.dist-info/licenses/LICENSE
woodwork_engine-0.2.11.dist-info/METADATA
woodwork_engine-0.2.11.dist-info/WHEEL
woodwork_engine-0.2.11.dist-info/entry_points.txt
woodwork_engine-0.2.11.dist-info/top_level.txt
woodwork_engine-0.2.11.dist-info/RECORD
