Metadata-Version: 2.4
Name: woodwork-engine
Version: 0.2.11
Summary: An AI Agent IaC tool that aims to make developing and deploying AI Agents easier.
Author: Will Woodward
Classifier: Programming Language :: Python :: 3.10
Classifier: Programming Language :: Python :: 3.11
Classifier: Programming Language :: Python :: 3.12
Classifier: Programming Language :: Python :: 3.13
Requires-Python: >=3.10
License-File: LICENSE
Requires-Dist: colorama>=0.4.6
Requires-Dist: deprecated>=1.2.18
Requires-Dist: distro>=1.9.0
Requires-Dist: idna>=3.10
Requires-Dist: jsonpointer>=3.0.0
Requires-Dist: python-dotenv>=1.1.0
Requires-Dist: pyyaml>=6.0.2
Requires-Dist: requests>=2.32.3
Requires-Dist: tomli>=2.2.1
Requires-Dist: uv>=0.7.12
Provides-Extra: all
Requires-Dist: chromadb>=1.0.12; extra == "all"
Requires-Dist: langchain>=0.3.25; extra == "all"
Requires-Dist: langchain-chroma>=0.2.4; extra == "all"
Requires-Dist: langchain-community>=0.3.24; extra == "all"
Requires-Dist: pytest>=8.3.5; extra == "all"
Requires-Dist: ruff>=0.11.12; extra == "all"
Requires-Dist: ty==0.0.1a9; extra == "all"
Requires-Dist: sentence-transformers>=4.1.0; extra == "all"
Dynamic: license-file
